odoo/addons/sale_invoice_plan/README.rst
odoo/addons/sale_invoice_plan/__init__.py
odoo/addons/sale_invoice_plan/__manifest__.py
odoo/addons/sale_invoice_plan/data/sale_data.xml
odoo/addons/sale_invoice_plan/i18n/es.po
odoo/addons/sale_invoice_plan/i18n/fr.po
odoo/addons/sale_invoice_plan/i18n/it.po
odoo/addons/sale_invoice_plan/i18n/nl_NL.po
odoo/addons/sale_invoice_plan/i18n/sale_invoice_plan.pot
odoo/addons/sale_invoice_plan/i18n/zh_CN.po
odoo/addons/sale_invoice_plan/models/__init__.py
odoo/addons/sale_invoice_plan/models/sale.py
odoo/addons/sale_invoice_plan/models/sale_invoice_plan.py
odoo/addons/sale_invoice_plan/readme/CONTRIBUTORS.md
odoo/addons/sale_invoice_plan/readme/CREDITS.md
odoo/addons/sale_invoice_plan/readme/DESCRIPTION.md
odoo/addons/sale_invoice_plan/readme/HISTORY.md
odoo/addons/sale_invoice_plan/readme/INSTALL.md
odoo/addons/sale_invoice_plan/readme/USAGE.md
odoo/addons/sale_invoice_plan/security/ir.model.access.csv
odoo/addons/sale_invoice_plan/static/description/icon.png
odoo/addons/sale_invoice_plan/static/description/index.html
odoo/addons/sale_invoice_plan/tests/__init__.py
odoo/addons/sale_invoice_plan/tests/test_sale_invoice_plan.py
odoo/addons/sale_invoice_plan/views/sale_view.xml
odoo/addons/sale_invoice_plan/wizard/__init__.py
odoo/addons/sale_invoice_plan/wizard/sale_create_invoice_plan.py
odoo/addons/sale_invoice_plan/wizard/sale_create_invoice_plan_view.xml
odoo/addons/sale_invoice_plan/wizard/sale_make_invoice_advance.py
odoo/addons/sale_invoice_plan/wizard/sale_make_planned_invoice.py
odoo/addons/sale_invoice_plan/wizard/sale_make_planned_invoice_view.xml
odoo_addon_sale_invoice_plan-17.0.1.0.1.dist-info/METADATA
odoo_addon_sale_invoice_plan-17.0.1.0.1.dist-info/WHEEL
odoo_addon_sale_invoice_plan-17.0.1.0.1.dist-info/top_level.txt
odoo_addon_sale_invoice_plan-17.0.1.0.1.dist-info/RECORD
