Metadata-Version: 2.1
Name: odoo-addon-sale_invoice_plan
Version: 17.0.1.0.1
Requires-Python: >=3.10
Requires-Dist: odoo>=17.0a,<17.1dev
Summary: Add to sales order, ability to manage future invoice plan
Home-page: https://github.com/OCA/sale-workflow
License: AGPL-3
Author: Ecosoft,Odoo Community Association (OCA)
Author-email: support@odoo-community.org
Classifier: Programming Language :: Python
Classifier: Framework :: Odoo
Classifier: Framework :: Odoo :: 17.0
Classifier: License :: OSI Approved :: GNU Affero General Public License v3
Classifier: Development Status :: 5 - Production/Stable
